easy_tormysql/__init__.py
easy_tormysql/db_exceptions.py
easy_tormysql/db_field.py
easy_tormysql/db_utils.py
easy_tormysql/model_base.py
easy_tormysql/models.py
easy_tormysql/query.py
easy_tormysql/rel.py
easy_tormysql/platform/__init__.py
easy_tormysql-0.2.4.dist-info/METADATA
easy_tormysql-0.2.4.dist-info/WHEEL
easy_tormysql-0.2.4.dist-info/top_level.txt
easy_tormysql-0.2.4.dist-info/RECORD
