Metadata-Version: 2.1
Name: easy-tormysql
Version: 0.2.4
Summary: This module provides a twice encapsulation of TorMySql based on Django's code style.
Home-page: https://github.com/encodingForBetterWorld/easy_tormysql
Author: NightRaven
Author-email: 1453878150@qq.com
License: UNKNOWN
Platform: UNKNOWN
Classifier: Programming Language :: Python :: 2
Classifier: Programming Language :: Python :: 3
Classifier: Operating System :: OS Independent
Requires-Dist: tormysql (==0.4.0)
